bbox/__init__.py
bbox/bbox2d.py
bbox/bbox2d_list.py
bbox/bbox3d.py
bbox/box_modes.py
bbox/geometry.py
bbox/metrics.py
bbox/utils.py
bbox-0.9.4.dist-info/LICENSE
bbox-0.9.4.dist-info/METADATA
bbox-0.9.4.dist-info/WHEEL
bbox-0.9.4.dist-info/RECORD
