Metadata-Version: 2.1
Name: bbox
Version: 0.9.4
Summary: Python library for 2D/3D bounding boxes
License: MIT
Author: Varun Agrawal
Author-email: varagrawal@gmail.com
Requires-Python: >=3.8
Classifier: License :: OSI Approved :: MIT License
Classifier: Programming Language :: Python :: 3
Classifier: Programming Language :: Python :: 3.8
Classifier: Programming Language :: Python :: 3.9
Classifier: Programming Language :: Python :: 3.10
Classifier: Programming Language :: Python :: 3.11
Requires-Dist: numpy (>=1.22.0,<2.0.0)
Requires-Dist: pyquaternion (>=0.9.5,<0.10.0)
